{
  "main": {
    "id": "2b6bcf90e061bb77",
    "type": "split",
    "children": [
      {
        "id": "91b634153916c465",
        "type": "split",
        "children": [
          {
            "id": "b71db4b7192cc613",
            "type": "tabs",
            "children": [
              {
                "id": "330e5a0e631ce83f",
                "type": "leaf",
                "state": {
                  "type": "markdown",
                  "state": {
                    "file": "GT/courses that I want to take at GATECH.md",
                    "mode": "source",
                    "source": false
                  }
                }
              },
              {
                "id": "2d61c7785c81a42a",
                "type": "leaf",
                "state": {
                  "type": "markdown",
                  "state": {
                    "file": "GT/resources.md",
                    "mode": "source",
                    "source": false
                  }
                }
              },
              {
                "id": "c67248e6bfaaa21c",
                "type": "leaf",
                "state": {
                  "type": "markdown",
                  "state": {
                    "file": "GT/courses that I want to take at GATECH.md",
                    "mode": "source",
                    "source": false
                  }
                }
              }
            ]
          },
          {
            "id": "0da566c03d4726e8",
            "type": "tabs",
            "children": [
              {
                "id": "f92b793b94a01514",
                "type": "leaf",
                "pinned": true,
                "state": {
                  "type": "terminal:terminal",
                  "state": {
                    "terminal:terminal": {
                      "cwd": "E:\\bens_vault",
                      "focus": false,
                      "profile": {
                        "args": [],
                        "executable": "C:\\Program Files\\Git\\bin\\bash.exe",
                        "name": "gitbash",
                        "platforms": {
                          "win32": true
                        },
                        "pythonExecutable": "python3",
                        "restoreHistory": true,
                        "successExitCodes": [
                          "0",
                          "SIGINT",
                          "SIGTERM"
                        ],
                        "terminalOptions": {},
                        "type": "integrated",
                        "useWin32Conhost": true
                      },
                      "serial": {
                        "columns": 170,
                        "data": "\r\n\u001b[32mrcmas@DESKTOP-CSMPT1J \u001b[35mMINGW64 \u001b[33m/e/bens_vault\u001b[36m (master)\r\n\u001b[0m$ git status\r\nOn branch master\r\nYour branch is up to date with 'origin/master'.\r\n\r\nChanges not staged for commit:\r\n  (use \"git add <file>...\" to update what will be committed)\r\n  (use \"git restore <file>...\" to discard changes in working directory)\r\n        \u001b[31mmodified:   .obsidian/workspace.json\r\n\r\n\u001b[0mno changes added to commit (use \"git add\" and/or \"git commit -a\")\r\n\r\n\u001b[32mrcmas@DESKTOP-CSMPT1J \u001b[35mMINGW64 \u001b[33m/e/bens_vault\u001b[36m (master)\r\n\u001b[0m$ git add .",
                        "rows": 57
                      }
                    }
                  },
                  "pinned": true
                }
              }
            ]
          }
        ],
        "direction": "horizontal"
      }
    ],
    "direction": "vertical"
  },
  "left": {
    "id": "9a76712c6e79b60e",
    "type": "split",
    "children": [
      {
        "id": "1c54e157b7c68e53",
        "type": "tabs",
        "children": [
          {
            "id": "dab9e94c482c8678",
            "type": "leaf",
            "state": {
              "type": "file-explorer",
              "state": {
                "sortOrder": "alphabetical"
              }
            }
          },
          {
            "id": "b8d195121472cad5",
            "type": "leaf",
            "state": {
              "type": "search",
              "state": {
                "query": "",
                "matchingCase": false,
                "explainSearch": false,
                "collapseAll": false,
                "extraContext": false,
                "sortOrder": "alphabetical"
              }
            }
          },
          {
            "id": "e00cc937e86b511e",
            "type": "leaf",
            "state": {
              "type": "bookmarks",
              "state": {}
            }
          }
        ]
      }
    ],
    "direction": "horizontal",
    "width": 300
  },
  "right": {
    "id": "4a99f62de6f785e8",
    "type": "split",
    "children": [
      {
        "id": "8349e6068269f090",
        "type": "tabs",
        "children": [
          {
            "id": "32d49d377fcf2f76",
            "type": "leaf",
            "state": {
              "type": "backlink",
              "state": {
                "collapseAll": false,
                "extraContext": false,
                "sortOrder": "alphabetical",
                "showSearch": false,
                "searchQuery": "",
                "backlinkCollapsed": false,
                "unlinkedCollapsed": true
              }
            }
          },
          {
            "id": "7d34582fb9135515",
            "type": "leaf",
            "state": {
              "type": "outgoing-link",
              "state": {
                "linksCollapsed": false,
                "unlinkedCollapsed": true
              }
            }
          },
          {
            "id": "240cdd382a8fe108",
            "type": "leaf",
            "state": {
              "type": "tag",
              "state": {
                "sortOrder": "frequency",
                "useHierarchy": true
              }
            }
          },
          {
            "id": "f860d66f6e5b942c",
            "type": "leaf",
            "state": {
              "type": "outline",
              "state": {}
            }
          }
        ]
      }
    ],
    "direction": "horizontal",
    "width": 300,
    "collapsed": true
  },
  "left-ribbon": {
    "hiddenItems": {
      "switcher:Open quick switcher": false,
      "graph:Open graph view": false,
      "canvas:Create new canvas": false,
      "daily-notes:Open today's daily note": false,
      "templates:Insert template": false,
      "command-palette:Open command palette": false,
      "terminal:Open terminal": false
    }
  },
  "active": "f92b793b94a01514",
  "lastOpenFiles": [
    "GT/courses that I want to take at GATECH.md",
    "GT/resources.md",
    "GT/Untitled.md",
    "RoboNav/generic VCU ideas and requirements.md",
    "nix stuff.md",
    "RoboNav/journey.canvas",
    "Stuff to get at store.md",
    "RoboNav/3D SLAM and graph based SLAM.md",
    "RoboNav/a better development method.md",
    "RoboNav/the new gazebo.md",
    "RoboNav/terrain mapping.md",
    "RoboNav/robonav URC background.md",
    "RoboNav/ROS2 features that could be very useful.md",
    "GT",
    "Untitled.canvas",
    "RoboNav"
  ]
}